README.rst
setup.py
germaniumdrivers/__init__.py
germaniumdrivers/available_driver.py
germaniumdrivers/configurable_settings.py
germaniumdrivers/driver_registry.py
germaniumdrivers/ensure_driver.py
germaniumdrivers/install_driver.py
germaniumdrivers/sha_hash.py
germaniumdrivers.egg-info/PKG-INFO
germaniumdrivers.egg-info/SOURCES.txt
germaniumdrivers.egg-info/dependency_links.txt
germaniumdrivers.egg-info/top_level.txt
germaniumdrivers/binary/chrome/linux/64/__init__.py
germaniumdrivers/binary/chrome/linux/64/chromedriver
germaniumdrivers/binary/chrome/mac/64/__init__.py
germaniumdrivers/binary/chrome/mac/64/chromedriver
germaniumdrivers/binary/chrome/win/32/__init__.py
germaniumdrivers/binary/chrome/win/32/chromedriver.exe
germaniumdrivers/binary/firefox/linux/64/__init__.py
germaniumdrivers/binary/firefox/linux/64/geckodriver
germaniumdrivers/binary/firefox/mac/32/__init__.py
germaniumdrivers/binary/firefox/mac/32/geckodriver
germaniumdrivers/binary/firefox/win/64/__init__.py
germaniumdrivers/binary/firefox/win/64/geckodriver.exe
germaniumdrivers/binary/ie/win/32/IEDriverServer.exe
germaniumdrivers/binary/ie/win/32/__init__.py
germaniumdrivers/binary/ie/win/64/IEDriverServer.exe
germaniumdrivers/binary/ie/win/64/__init__.py