Metadata-Version: 1.0
Name: germaniumdrivers
Version: 2.0.9
Summary: The germanium project: Selenium WebDriver testing API that doesn't disappoint. (tested WebDrivers package)
Home-page: UNKNOWN
Author: Bogdan Mustiata
Author-email: bogdan.mustiata@gmail.com
License: BSD
Platform: UNKNOWN
